easier_sockets/__init__.py
easier_sockets/easier_sockets.py
easier_sockets-0.0.6.dist-info/METADATA
easier_sockets-0.0.6.dist-info/WHEEL
easier_sockets-0.0.6.dist-info/top_level.txt
easier_sockets-0.0.6.dist-info/RECORD
